Workbook

Sheet 0. The Problem

Sheet 1.  Pro Forma Income Statement
A1: Advanced Hip Replacement Implant Technology Pro Forma
A3: Tax Rate: | B3: 0.21
A4: Discount Rate: | B4: 0.18
B6: Year
A7: Revenues: | B7: 1 | C7: 2 | D7: 3 | E7: 4 | F7: 5 | G7: 6 | H7: 7 | I7: 8 | J7: 9 | K7: 10
A8: Unit Price: | B8: 5000 | C8: 5000 | D8: 5000 | E8: 5000 | F8: 5000 | G8: 5000 | H8: 5000 | I8: 5000 | J8: 5000 | K8: 5000
A9: Unit Sales: | B9: =5000 -> 5000 | C9: =B9*(1+10%) -> 5500 | D9: =C9*(1+10%) -> 6050 | E9: =D9*(1+10%) -> 6655 | F9: =E9*(1+10%) -> 7320.5 | G9: =F9*(1+10%) -> 8052.55 | H9: =G9*(1+10%) -> 8857.805 | I9: =H9*(1+10%) -> 9743.5855 | J9: =I9*(1+10%) -> 10717.944 | K9: =J9*(1+10%) -> 11789.738
A10: Revenues: | B10: =B8*B9 -> 25000000 | C10: =C8*C9 -> 27500000 | D10: =D8*D9 -> 30250000 | E10: =E8*E9 -> 33275000 | F10: =F8*F9 -> 36602500 | G10: =G8*G9 -> 40262750 | H10: =H8*H9 -> 44289025 | I10: =I8*I9 -> 48717928 | ... K10: =K8*K9 -> 58948692
A12: COGS:
A13: Unit Cost | B13: 3000 | C13: =B13*(1-2%) -> 2940 | D13: =C13*(1-2%) -> 2881.2 | E13: =D13*(1-2%) -> 2823.576 | F13: =E13*(1-2%) -> 2767.1045 | G13: =F13*(1-2%) -> 2711.7624 | H13: =G13*(1-2%) -> 2657.5271 | I13: =H13*(1-2%) -> 2604.3766 | J13: =I13*(1-2%) -> 2552.2891 | K13: =J13*(1-2%) -> 2501.2433
A14: COGS: | B14: =B13*B9 -> 15000000 | C14: =C13*C9 -> 16170000 | D14: =D13*D9 -> 17431260 | E14: =E13*E9 -> 18790898 | F14: =F13*F9 -> 20256588 | G14: =G13*G9 -> 21836602 | H14: =H13*H9 -> 23539857 | I14: =I13*I9 -> 25375966 | ... K14: =K13*K9 -> 29489004
A16: Gross Profit: | B16: =B10-B14 -> 10000000 | C16: =C10-C14 -> 11330000 | D16: =D10-D14 -> 12818740 | E16: =E10-E14 -> 14484102 | F16: =F10-F14 -> 16345912 | G16: =G10-G14 -> 18426148 | H16: =H10-H14 -> 20749168 | I16: =I10-I14 -> 23341961 | ... K16: =K10-K14 -> 29459688
A18: Operating Expenses:
A19: Engineering | B19: 1500000 | C19: 1500000 | D19: 1500000 | E19: 1000000 | F19: 1000000 | G19: 1000000 | H19: 500000 | I19: 500000 | J19: 500000 | K19: 500000
A20: Marketing & Sales | B20: 1000000 | C20: 1000000 | D20: 1000000 | E20: 1000000 | F20: 1000000 | G20: 1000000 | H20: 1000000 | I20: 1000000 | J20: 1000000 | K20: 1000000
A21: Legal (IP) | B21: 250000 | C21: 250000 | D21: 100000 | E21: 100000 | F21: 100000 | G21: 100000 | H21: 100000 | I21: 100000 | J21: 100000 | K21: 100000
A22: Depreciation Expense: | B22: ='2. Depreciation'!C6 -> 2858000 | C22: ='2. Depreciation'!C7 -> 4898000 | D22: ='2. Depreciation'!C8 -> 3498000 | E22: ='2. Depreciation'!C9 -> 2498000 | F22: ='2. Depreciation'!C10 -> 1786000 | G22: ='2. Depreciation'!C11 -> 1784000 | H22: ='2. Depreciation'!C12 -> 1786000 | I22: ='2. Depreciation'!C13 -> 892000
A23: Total Operating Expenses: | B23: =SUM(B19:B22) -> 5608000 | C23: =SUM(C19:C22) -> 7648000 | D23: =SUM(D19:D22) -> 6098000 | E23: =SUM(E19:E22) -> 4598000 | F23: =SUM(F19:F22) -> 3886000 | G23: =SUM(G19:G22) -> 3884000 | H23: =SUM(H19:H22) -> 3386000 | I23: =SUM(I19:I22) -> 2492000 | ... K23: =SUM(K19:K22) -> 1600000
A25: Operating Income (EBIT): | B25: =B16-B23 -> 4392000 | C25: =C16-C23 -> 3682000 | D25: =D16-D23 -> 6720740 | E25: =E16-E23 -> 9886101.7 | F25: =F16-F23 -> 12459912 | G25: =G16-G23 -> 14542148 | H25: =H16-H23 -> 17363168 | I25: =I16-I23 -> 20849961 | ... K25: =K16-K23 -> 27859688
A27: Taxes (@21%) | B27: =21%*B25 -> 922320 | C27: =21%*C25 -> 773220 | D27: =21%*D25 -> 1411355.4 | E27: =21%*E25 -> 2076081.4 | F27: =21%*F25 -> 2616581.4 | G27: =21%*G25 -> 3053851 | H27: =21%*H25 -> 3646265.2 | I27: =21%*I25 -> 4378491.9 | ... K27: =21%*K25 -> 5850534.5
A29: Net Income: | B29: =B25-B27 -> 3469680 | C29: =C25-C27 -> 2908780 | D29: =D25-D27 -> 5309384.6 | E29: =E25-E27 -> 7810020.4 | F29: =F25-F27 -> 9843330.2 | G29: =G25-G27 -> 11488297 | H29: =H25-H27 -> 13716903 | I29: =I25-I27 -> 16471470 | ... K29: =K25-K27 -> 22009154

Sheet 2.  Depreciation
A1: Depreciation Expense Calculations
A3: CAPEX: | B3: 20000000
A5: Year | B5: MACRS % | C5: Depreciation | D5: Book Value
A6: 1 | B6: 0.1429 | C6: =$B$3*B6 -> 2858000 | D6: =$B$3-C6 -> 17142000
A7: 2 | B7: 0.2449 | C7: =$B$3*B7 -> 4898000 | D7: =D6-C7 -> 12244000
A8: 3 | B8: 0.1749 | C8: =$B$3*B8 -> 3498000 | D8: =D7-C8 -> 8746000
A9: 4 | B9: 0.1249 | C9: =$B$3*B9 -> 2498000 | D9: =D8-C9 -> 6248000
A10: 5 | B10: 0.0893 | C10: =$B$3*B10 -> 1786000 | D10: =D9-C10 -> 4462000
A11: 6 | B11: 0.0892 | C11: =$B$3*B11 -> 1784000 | D11: =D10-C11 -> 2678000
A12: 7 | B12: 0.0893 | C12: =$B$3*B12 -> 1786000 | D12: =D11-C12 -> 892000
A13: 8 | B13: 0.0446 | C13: =$B$3*B13 -> 892000 | D13: =D12-C13 -> 0

Sheet 3.  CF-Operations
A1: Cash Flow from Operations
B3: Year
B4: 0 | C4: 1 | D4: 2 | E4: 3 | F4: 4 | G4: 5 | H4: 6 | I4: 7 | J4: 8 | K4: 9 | L4: 10
A5: EBIT | B5: 0 | C5: ='1. Pro Forma Income Statement'!B25 -> 4392000 | D5: ='1. Pro Forma Income Statement'!C25 -> 3682000 | E5: ='1. Pro Forma Income Statement'!D25 -> 6720740 | F5: ='1. Pro Forma Income Statement'!E25 -> 9886101.7 | G5: ='1. Pro Forma Income Statement'!F25 -> 12459912 | H5: ='1. Pro Forma Income Statement'!G25 -> 14542148 | I5: ='1. Pro Forma Income Statement'!H25 -> 17363168 | J5: ='1. Pro Forma Income Statement'!I25 -> 20849961 | ... L5: ='1. Pro Forma Income Statement'!K25 -> 27859688
A6: + Depreciation | B6: 0 | C6: ='1. Pro Forma Income Statement'!B22 -> 2858000 | D6: ='1. Pro Forma Income Statement'!C22 -> 4898000 | E6: ='1. Pro Forma Income Statement'!D22 -> 3498000 | F6: ='1. Pro Forma Income Statement'!E22 -> 2498000 | G6: ='1. Pro Forma Income Statement'!F22 -> 1786000 | H6: ='1. Pro Forma Income Statement'!G22 -> 1784000 | I6: ='1. Pro Forma Income Statement'!H22 -> 1786000 | J6: ='1. Pro Forma Income Statement'!I22 -> 892000
A7: - Taxes | B7: 0 | C7: ='1. Pro Forma Income Statement'!B27 -> 922320 | D7: ='1. Pro Forma Income Statement'!C27 -> 773220 | E7: ='1. Pro Forma Income Statement'!D27 -> 1411355.4 | F7: ='1. Pro Forma Income Statement'!E27 -> 2076081.4 | G7: ='1. Pro Forma Income Statement'!F27 -> 2616581.4 | H7: ='1. Pro Forma Income Statement'!G27 -> 3053851 | I7: ='1. Pro Forma Income Statement'!H27 -> 3646265.2 | J7: ='1. Pro Forma Income Statement'!I27 -> 4378491.9 | ... L7: ='1. Pro Forma Income Statement'!K27 -> 5850534.5
A8: Cash Flows from Operations | B8: =B5+B6-B7 -> 0 | C8: =C5+C6-C7 -> 6327680 | D8: =D5+D6-D7 -> 7806780 | E8: =E5+E6-E7 -> 8807384.6 | F8: =F5+F6-F7 -> 10308020 | G8: =G5+G6-G7 -> 11629330 | H8: =H5+H6-H7 -> 13272297 | I8: =I5+I6-I7 -> 15502903 | ... L8: =L5+L6-L7 -> 22009154

Sheet 4. CF-NWC
A1: Cash Flow due to Change in Net Working Capital
B4: Year
B5: 0 | C5: 1 | D5: 2 | E5: 3 | F5: 4 | G5: 5 | H5: 6 | I5: 7 | J5: 8 | K5: 9 | L5: 10
A6: Revenues: | B6: 0 | C6: ='1. Pro Forma Income Statement'!B10 -> 25000000 | D6: ='1. Pro Forma Income Statement'!C10 -> 27500000 | E6: ='1. Pro Forma Income Statement'!D10 -> 30250000 | F6: ='1. Pro Forma Income Statement'!E10 -> 33275000 | G6: ='1. Pro Forma Income Statement'!F10 -> 36602500 | H6: ='1. Pro Forma Income Statement'!G10 -> 40262750 | I6: ='1. Pro Forma Income Statement'!H10 -> 44289025 | J6: ='1. Pro Forma Income Statement'!I10 -> 48717928 | ... L6: ='1. Pro Forma Income Statement'!K10 -> 58948692
A7: NWC (Inventory, end of year) | B7: 2500000 | C7: =15%*C6 -> 3750000 | D7: =15%*D6 -> 4125000 | E7: =15%*E6 -> 4537500 | F7: =15%*F6 -> 4991250 | G7: =15%*G6 -> 5490375 | H7: =15%*H6 -> 6039412.5 | I7: =15%*I6 -> 6643353.8 | J7: =15%*J6 -> 7307689.1 | ... L7: =15%*L6 -> 8842303.8
A8: DNWC | B8: =B7 -> 2500000 | C8: =C7-B7 -> 1250000 | D8: =D7-C7 -> 375000 | E8: =E7-D7 -> 412500 | F8: =F7-E7 -> 453750 | G8: =G7-F7 -> 499125 | H8: =H7-G7 -> 549037.5 | I8: =I7-H7 -> 603941.25 | J8: =J7-I7 -> 664335.38 | ... L8: =L7-K7 -> 803845.8
A9: NWC Recovery | L9: =L7 -> 8842303.8
A10: Cash Flows from DNWC | B10: =-B8 -> -2500000 | C10: =-C8 -> -1250000 | D10: =-D8 -> -375000 | E10: =-E8 -> -412500 | F10: =-F8 -> -453750 | G10: =-G8 -> -499125 | H10: =-H8 -> -549037.5 | I10: =-I8 -> -603941.25 | ... K10: =-K8 -> -730768.91 | L10: =-L8+L9 -> 8038458

Sheet 5. CF-Capital Spending
A1: Cash Flow due to Capital Spending
B4: Year
B5: 0 | C5: 1 | D5: 2 | E5: 3 | F5: 4 | G5: 5 | H5: 6 | I5: 7 | J5: 8 | K5: 9 | L5: 10
A6: CAPEX | B6: =-'2. Depreciation'!B3 -> -20000000 | C6: 0 | D6: 0 | E6: 0 | F6: 0 | G6: 0 | H6: 0 | I6: 0 | J6: 0 | K6: 0 | L6: 0
A7: After-Tax Salvage Value | L7: =2000000*(1-21%) -> 1580000
A8: Cash Flows from Capital Spending | B8: =SUM(B6:B7) -> -20000000 | C8: =SUM(C6:C7) -> 0 | D8: =SUM(D6:D7) -> 0 | E8: =SUM(E6:E7) -> 0 | F8: =SUM(F6:F7) -> 0 | G8: =SUM(G6:G7) -> 0 | H8: =SUM(H6:H7) -> 0 | I8: =SUM(I6:I7) -> 0 | ... L8: =SUM(L6:L7) -> 1580000

Sheet 6.  Final Analysis-NPV_IRR_PBP
A1: Project Pro Forma Cash Flows
A3: Discount Rate: | B3: 0.18
B5: Year
B6: 0 | C6: 1 | D6: 2 | E6: 3 | F6: 4 | G6: 5 | H6: 6 | I6: 7 | J6: 8 | K6: 9 | L6: 10
A7: Cash Flows from Operations: | B7: ='3. CF-Operations'!B8 -> 0 | C7: ='3. CF-Operations'!C8 -> 6327680 | D7: ='3. CF-Operations'!D8 -> 7806780 | E7: ='3. CF-Operations'!E8 -> 8807384.6 | F7: ='3. CF-Operations'!F8 -> 10308020 | G7: ='3. CF-Operations'!G8 -> 11629330 | H7: ='3. CF-Operations'!H8 -> 13272297 | I7: ='3. CF-Operations'!I8 -> 15502903 | ... L7: ='3. CF-Operations'!L8 -> 22009154
A8: Cash Flow from DNWC | B8: ='4. CF-NWC'!B10 -> -2500000 | C8: ='4. CF-NWC'!C10 -> -1250000 | D8: ='4. CF-NWC'!D10 -> -375000 | E8: ='4. CF-NWC'!E10 -> -412500 | F8: ='4. CF-NWC'!F10 -> -453750 | G8: ='4. CF-NWC'!G10 -> -499125 | H8: ='4. CF-NWC'!H10 -> -549037.5 | I8: ='4. CF-NWC'!I10 -> -603941.25 | ... L8: ='4. CF-NWC'!L10 -> 8038458
A9: Cash Flows from Capital Spending: | B9: ='5. CF-Capital Spending'!B8 -> -20000000 | C9: ='5. CF-Capital Spending'!C8 -> 0 | D9: ='5. CF-Capital Spending'!D8 -> 0 | E9: ='5. CF-Capital Spending'!E8 -> 0 | F9: ='5. CF-Capital Spending'!F8 -> 0 | G9: ='5. CF-Capital Spending'!G8 -> 0 | H9: ='5. CF-Capital Spending'!H8 -> 0 | I9: ='5. CF-Capital Spending'!I8 -> 0 | ... L9: ='5. CF-Capital Spending'!L8 -> 1580000
A10: Total Project Cash Flow: | B10: =SUM(B7:B9) -> -22500000 | C10: =SUM(C7:C9) -> 5077680 | D10: =SUM(D7:D9) -> 7431780 | E10: =SUM(E7:E9) -> 8394884.6 | F10: =SUM(F7:F9) -> 9854270.4 | G10: =SUM(G7:G9) -> 11130205 | H10: =SUM(H7:H9) -> 12723259 | I10: =SUM(I7:I9) -> 14898961 | ... L10: =SUM(L7:L9) -> 31627612
A11: Cumulative Project Cash Flows: | B11: =B10 -> -22500000 | C11: =B11+C10 -> -17422320 | D11: =C11+D10 -> -9990540 | E11: =D11+E10 -> -1595655.4 | F11: =E11+F10 -> 8258615 | G11: =F11+G10 -> 19388820 | H11: =G11+H10 -> 32112079 | I11: =H11+I10 -> 47011041 | J11: =I11+J10 -> 63710175 | ... L11: =K11+L10 -> 1.1406822e+08
A14: PV (Year 1-10): | B14: =NPV(B3,C10:L10) -> 48796394
A15: Initial Investment (Cash Flow): | B15: =B10 -> -22500000
A16: NPV: | B16: =B14+B15 -> 26296394
A17: IRR: | B17: =IRR(B10:L10) -> 0.38266942
A18: Simple Payback Period (years): | B18: =3+(-E11/F10) -> 3.1619253
